MANIFEST.in
README
setup.py
vmerlin/__init__.py
vmerlin/agent.py
vmerlin/bottleweaver.py
vmerlin/dbweaver.py
vmerlin/dispatcher.py
vmerlin/djangoweaver.py
vmerlin/genericweaver.py
vmerlin/helpers.py
vmerlin/httpweaver.py
vmerlin/logger.py
vmerlin/mysqlweaver.py
vmerlin/pymongoweaver.py
vmerlin/redisweaver.py
vmerlin/sender.py
vmerlin/sqlite3weaver.py
vmerlin/tornadoweaver.py
vmerlin/version.py
vmerlin.egg-info/PKG-INFO
vmerlin.egg-info/SOURCES.txt
vmerlin.egg-info/dependency_links.txt
vmerlin.egg-info/requires.txt
vmerlin.egg-info/top_level.txt
vmerlin/config/config.defaults.json
vmerlin/config/vmerlin.config.json