Metadata-Version: 1.1
Name: vmerlin
Version: 1.0.11
Summary: vMerlin Python agent
Home-page: https://vmerlin.cf/
Author: Goldstein Lyor
Author-email: lgoldstein@vmware.com
License: Vmware Ltd.
Keywords: application,performance,monitoring
Platform: Linux
Platform: Windows
Platform: MacOS
Classifier: Development Status :: 2 - Pre-Alpha
Classifier: Environment :: Web Environment
Classifier: Intended Audience :: Developers
Classifier: Intended Audience :: System Administrators
Classifier: License :: Other/Proprietary License
Classifier: Operating System :: MacOS
Classifier: Operating System :: Microsoft :: Windows
Classifier: Operating System :: POSIX
Classifier: Programming Language :: Python
Classifier: Topic :: System :: Monitoring
